mkapi/__init__.py
mkapi/config.py
mkapi/css/mkapi-common.css
mkapi/css/mkapi-material.css
mkapi/javascript/mkapi.js
mkapi/nav.py
mkapi/page.py
mkapi/parser.py
mkapi/plugin.py
mkapi/py.typed
mkapi/renderer.py
mkapi/templates/document.jinja2
mkapi/templates/heading.jinja2
mkapi/templates/object.jinja2
mkapi/templates/source.jinja2
mkapi-4.5.0.dist-info/WHEEL
mkapi-4.5.0.dist-info/entry_points.txt
mkapi-4.5.0.dist-info/METADATA
mkapi-4.5.0.dist-info/RECORD
