Metadata-Version: 2.3
Name: mkapi
Version: 4.5.0
Summary: MkDocs plugin for automatic API documentation generation from Python docstrings
Keywords: mkdocs,documentation,api,docstring,markdown
Author: daizutabi
Author-email: daizutabi <daizutabi@gmail.com>
License: MIT License
Classifier: Development Status :: 5 - Production/Stable
Classifier: Framework :: MkDocs
Classifier: Intended Audience :: Developers
Classifier: License :: OSI Approved :: MIT License
Classifier: Operating System :: OS Independent
Classifier: Programming Language :: Python :: 3.10
Classifier: Programming Language :: Python :: 3.11
Classifier: Programming Language :: Python :: 3.12
Classifier: Programming Language :: Python :: 3.13
Classifier: Programming Language :: Python :: 3.14
Classifier: Programming Language :: Python
Classifier: Topic :: Documentation
Classifier: Topic :: Software Development :: Documentation
Classifier: Topic :: Software Development :: Libraries :: Python Modules
Classifier: Topic :: Text Processing :: Markup :: Markdown
Classifier: Typing :: Typed
Requires-Dist: astdoc>=1.3.0
Requires-Dist: jinja2
Requires-Dist: mkdocs-material
Requires-Dist: mkdocs>=1.6.0
Requires-Dist: tomli>=1.1.0 ; python_full_version < '3.11'
Requires-Python: >=3.10
Project-URL: Documentation, https://daizutabi.github.io/mkapi/
Project-URL: Issues, https://github.com/daizutabi/mkapi/issues
Project-URL: Source, https://github.com/daizutabi/mkapi
